pyraws/__init__.py
pyraws/sys_cfg.py
pyraws/l1/l1_event.py
pyraws/l1/l1_tile.py
pyraws/raw/raw_event.py
pyraws/raw/raw_granule.py
pyraws/utils/band_shape_utils.py
pyraws/utils/constants.py
pyraws/utils/database_utils.py
pyraws/utils/date_utils.py
pyraws/utils/l1_utils.py
pyraws/utils/parse_csv_utils.py
pyraws/utils/raw_utils.py
pyraws/utils/shape_utils.py
pyraws/utils/visualization_utils.py
pyraws-0.0.3.dist-info/LICENSE
pyraws-0.0.3.dist-info/METADATA
pyraws-0.0.3.dist-info/WHEEL
pyraws-0.0.3.dist-info/top_level.txt
pyraws-0.0.3.dist-info/RECORD
