Metadata-Version: 2.1
Name: pyraws
Version: 0.0.3
Summary: Python for RAW Sentinel2 data (PyRawS) is a powerful open-source Python package that provides a comprehensive set of tools for working with Sentinel-2 Raw data. It provides utilities for coarse spatial bands coregistration, geo-referencing, data visualization, and image processing.
Home-page: https://github.com/ESA-PhiLab/PyRawS
Author: ESA Philab
Author-email: gabriele.meoni@esa.int
License: UNKNOWN
Project-URL: Source, https://github.com/ESA-PhiLab/PyRawS
Platform: UNKNOWN
Classifier: Development Status :: 3 - Alpha
Classifier: Intended Audience :: Developers
Classifier: Intended Audience :: Science/Research
Classifier: Topic :: Scientific/Engineering :: GIS
Classifier: License :: OSI Approved :: GNU General Public License v3 (GPLv3)
Classifier: Programming Language :: Python :: 3.8
Classifier: Environment :: GPU :: NVIDIA CUDA :: 11.0
Requires-Python: >=3.8, <4
License-File: LICENSE
Requires-Dist: geopy
Requires-Dist: geopandas
Requires-Dist: glymur
Requires-Dist: numpy
Requires-Dist: opencv-python
Requires-Dist: pandas
Requires-Dist: scipy
Requires-Dist: matplotlib
Requires-Dist: termcolor
Requires-Dist: torch
Requires-Dist: tqdm
Requires-Dist: torchvision
Requires-Dist: scikit-image
Requires-Dist: scikit-learn
Requires-Dist: rasterio
Requires-Dist: tifffile
